[
  {
    "title": "Trump\u2019s Ambassador to Belgium Is Summoned After Accusing Officials of Antisemitism",
    "link": "https://www.nytimes.com/2026/02/17/world/europe/belgium-trump-ambassador-anti-semitism.html",
    "source": "New York Times",
    "published": "2026-02-17T17:47:24+00:00"
  },
  {
    "title": "Iranians Defy Government Crackdown at Memorials for Slain Protesters",
    "link": "https://www.nytimes.com/2026/02/17/world/middleeast/iran-memorials-protesters-crackdown.html",
    "source": "New York Times",
    "published": "2026-02-17T17:42:36+00:00"
  },
  {
    "title": "California Forecast: Storms to Bring More Snow and Rain",
    "link": "https://www.nytimes.com/2026/02/17/weather/california-rain-snow-forecast.html",
    "source": "New York Times",
    "published": "2026-02-17T17:42:14+00:00"
  },
  {
    "title": "Labour accepts the inevitable in local elections U-turn",
    "link": "https://www.bbc.com/news/articles/czx7n9n0xrro?at_medium=RSS&at_campaign=rss",
    "source": "BBC News",
    "published": "2026-02-17T17:28:26+00:00"
  },
  {
    "title": "Has Trump Thrown the Democrats a Lifesaver?",
    "link": "https://www.nytimes.com/2026/02/17/opinion/trump-coalition-multiracial-working-class.html",
    "source": "New York Times",
    "published": "2026-02-17T17:15:24+00:00"
  },
  {
    "title": "Questions Swirl Around Russian Figure Skater in Her Olympic Debut",
    "link": "https://www.nytimes.com/2026/02/17/world/europe/russian-figure-skater-milan-olympics.html",
    "source": "New York Times",
    "published": "2026-02-17T17:00:23+00:00"
  },
  {
    "title": "This backup camera cleaner hides behind your license plate",
    "link": "https://www.theverge.com/gadgets/877893/lens-lizard-backup-camera-cleaner-aftermarket-wiper-fluid-kickstarter",
    "source": "The Verge",
    "published": "2026-02-17T17:00:00+00:00"
  },
  {
    "title": "A photojournalist details her rebellion against the Syrian regime -- and her father",
    "link": "https://www.npr.org/2026/02/17/nx-s1-5717011/a-photojournalist-details-her-rebellion-against-the-syrian-regime-and-her-father",
    "source": "NPR",
    "published": "2026-02-17T16:55:02+00:00"
  },
  {
    "title": "Ukraine and Russia Hold New Round of Peace Talks, but Expectations Are Low",
    "link": "https://www.nytimes.com/2026/02/17/world/europe/ukraine-russia-peace-talks-switzerland.html",
    "source": "New York Times",
    "published": "2026-02-17T16:51:48+00:00"
  },
  {
    "title": "Dual nationals face scramble for British passports as new rules come into force",
    "link": "https://www.bbc.com/news/articles/cx2d9yk2kpjo?at_medium=RSS&at_campaign=rss",
    "source": "BBC News",
    "published": "2026-02-17T16:45:21+00:00"
  },
  {
    "title": "'The search is soul-destroying': Young jobseekers on the struggle to find work",
    "link": "https://www.bbc.com/news/articles/c3wl17l3ggqo?at_medium=RSS&at_campaign=rss",
    "source": "BBC News",
    "published": "2026-02-17T16:37:08+00:00"
  },
  {
    "title": "We don't want to see five years pass by just sitting idle: Showkat Aziz Russell",
    "link": "https://www.tbsnews.net/bangladesh/we-dont-want-see-five-years-pass-just-sitting-idle-showkat-aziz-russell-1364596",
    "source": "The Business Standard",
    "published": "2026-02-17T16:35:00+00:00"
  },
  {
    "title": "Alienware\u2019s fast 27-inch QD-OLED gaming monitor is 23 percent off",
    "link": "https://www.theverge.com/gadgets/879940/alienware-qd-oled-pc-gaming-monitor-switch-games-apple-watch-deal-sale",
    "source": "The Verge",
    "published": "2026-02-17T16:30:32+00:00"
  },
  {
    "title": "The Price of Admission to Epstein\u2019s World: Silence",
    "link": "https://www.nytimes.com/2026/02/17/well/epstein-files-associates.html",
    "source": "New York Times",
    "published": "2026-02-17T16:30:05+00:00"
  },
  {
    "title": "EC prepares for local govt elections including Dhaka, Ctg city corporations",
    "link": "https://www.tbsnews.net/bangladesh/ec-prepares-local-govt-elections-including-dhaka-ctg-city-corporations-1364586",
    "source": "The Business Standard",
    "published": "2026-02-17T16:30:00+00:00"
  },
  {
    "title": "'Very difficult to solve, but we will do homework': Iqbal Hasan on energy sector challenges",
    "link": "https://www.tbsnews.net/bangladesh/energy/very-difficult-solve-we-will-do-homework-iqbal-hasan-energy-sector-challenges",
    "source": "The Business Standard",
    "published": "2026-02-17T16:30:00+00:00"
  },
  {
    "title": "Singer and YouTuber who makes music with Furbys and Game Boys picked for UK at Eurovision",
    "link": "https://www.bbc.com/news/articles/clygz17y5kdo?at_medium=RSS&at_campaign=rss",
    "source": "BBC News",
    "published": "2026-02-17T16:26:36+00:00"
  },
  {
    "title": "Two general insurers declare dividends for 2025",
    "link": "https://www.tbsnews.net/economy/stocks/two-general-insurers-declare-dividends-2025-1364571",
    "source": "The Business Standard",
    "published": "2026-02-17T16:25:00+00:00"
  },
  {
    "title": "Premier Cement gets BSEC nod to raise Tk161cr through preference shares",
    "link": "https://www.tbsnews.net/economy/stocks/premier-cement-gets-bsec-nod-raise-tk161cr-through-preference-shares-1364556",
    "source": "The Business Standard",
    "published": "2026-02-17T16:20:00+00:00"
  },
  {
    "title": "Early rift over Reform Council oath casts shadow on political harmony",
    "link": "https://www.tbsnews.net/bangladesh/early-rift-over-reform-council-oath-casts-shadow-political-harmony-1364581",
    "source": "The Business Standard",
    "published": "2026-02-17T16:20:00+00:00"
  },
  {
    "title": "Stocks edge down as cautious investors watch new government take oath",
    "link": "https://www.tbsnews.net/economy/stocks/stocks-edge-down-cautious-investors-watch-new-government-take-oath-1364551",
    "source": "The Business Standard",
    "published": "2026-02-17T16:15:00+00:00"
  },
  {
    "title": "Reform names Robert Jenrick as pick for chancellor",
    "link": "https://www.bbc.com/news/articles/c33j7m7y17xo?at_medium=RSS&at_campaign=rss",
    "source": "BBC News",
    "published": "2026-02-17T16:14:16+00:00"
  },
  {
    "title": "Navana Pharmaceuticals' rejoinder and our reply",
    "link": "https://www.tbsnews.net/economy/stocks/navana-pharmaceuticals-rejoinder-and-our-reply-1364541",
    "source": "The Business Standard",
    "published": "2026-02-17T16:10:00+00:00"
  },
  {
    "title": "Experts urge review of Bangladesh-US tariff deal, cite risks to economy",
    "link": "https://www.tbsnews.net/bangladesh/experts-urge-review-bangladesh-us-tariff-deal-cite-risks-economy-1364561",
    "source": "The Business Standard",
    "published": "2026-02-17T16:10:00+00:00"
  },
  {
    "title": "New govt must take priority measures for rapid economic recovery: Taskeen Ahmed",
    "link": "https://www.tbsnews.net/bangladesh/new-govt-must-take-priority-measures-rapid-economic-recovery-taskeen-ahmed-1364526",
    "source": "The Business Standard",
    "published": "2026-02-17T16:00:00+00:00"
  },
  {
    "title": "Tarique visits parents\u2019 graves after being sworn in as PM",
    "link": "https://www.tbsnews.net/bangladesh/tarique-visits-parents-graves-after-being-sworn-pm-1364531",
    "source": "The Business Standard",
    "published": "2026-02-17T16:00:00+00:00"
  },
  {
    "title": "Ford is fighting against physics to build affordable EVs",
    "link": "https://www.theverge.com/transportation/879975/ford-universal-ev-platform-skunkworks-aero-battery-range",
    "source": "The Verge",
    "published": "2026-02-17T16:00:00+00:00"
  },
  {
    "title": "Ariful Haque's ascent from councillor to minister reads like a fairy tale",
    "link": "https://www.tbsnews.net/bangladesh/ariful-haques-ascent-councillor-minister-reads-fairy-tale-1364511",
    "source": "The Business Standard",
    "published": "2026-02-17T15:55:00+00:00"
  },
  {
    "title": "Why are some students claiming Covid compensation from universities?",
    "link": "https://www.bbc.com/news/articles/c3wl19wy22vo?at_medium=RSS&at_campaign=rss",
    "source": "BBC News",
    "published": "2026-02-17T15:53:25+00:00"
  },
  {
    "title": "Police identify suspect in Rhode Island ice rink shooting",
    "link": "https://www.bbc.com/news/articles/c75e7wqqq6no?at_medium=RSS&at_campaign=rss",
    "source": "BBC News",
    "published": "2026-02-17T15:47:53+00:00"
  },
  {
    "title": "Your next laptop could be a foldable phone",
    "link": "https://www.theverge.com/podcast/879965/foldable-phone-laptop-keyboard-sports-streaming-vergecast",
    "source": "The Verge",
    "published": "2026-02-17T15:46:44+00:00"
  },
  {
    "title": "Immediate action needed to improve law and order, stabilise prices: Mir Nasir Hossain",
    "link": "https://www.tbsnews.net/bangladesh/immediate-action-needed-improve-law-and-order-stabilise-prices-mir-nasir-hossain-1364491",
    "source": "The Business Standard",
    "published": "2026-02-17T15:45:00+00:00"
  },
  {
    "title": "Ramadan begins tomorrow in Saudi Arabia",
    "link": "https://www.tbsnews.net/bangladesh/ramadan-begins-tomorrow-saudi-arabia-1364496",
    "source": "The Business Standard",
    "published": "2026-02-17T15:45:00+00:00"
  },
  {
    "title": "A Holiday High-School Game Is Shattered by a Fatal Assault",
    "link": "https://www.nytimes.com/2026/02/17/us/rhode-island-hockey-rink-shooting.html",
    "source": "New York Times",
    "published": "2026-02-17T15:43:19+00:00"
  },
  {
    "title": "Surprised by the cabinet, but satisfied: KAS Murshid",
    "link": "https://www.tbsnews.net/bangladesh/surprised-cabinet-satisfied-kas-murshid-1364476",
    "source": "The Business Standard",
    "published": "2026-02-17T15:40:00+00:00"
  },
  {
    "title": "Coordinated action needed to tackle inflation, jobs, revenue weakness: Sayema Haque Bidisha",
    "link": "https://www.tbsnews.net/bangladesh/coordinated-action-needed-tackle-inflation-jobs-revenue-weakness-sayema-haque-bidisha",
    "source": "The Business Standard",
    "published": "2026-02-17T15:35:00+00:00"
  },
  {
    "title": "Balanced cabinet, well-placed to tackle mounting economic challenges: Masrur Reaz",
    "link": "https://www.tbsnews.net/bangladesh/balanced-cabinet-well-placed-tackle-mounting-economic-challenges-masrur-reaz-1364471",
    "source": "The Business Standard",
    "published": "2026-02-17T15:35:00+00:00"
  },
  {
    "title": "Stephen Colbert says CBS banned him from airing this James Talarico interview",
    "link": "https://www.theverge.com/policy/880009/stephen-colbert-cbs-fcc-brendan-carr-talarico-interview",
    "source": "The Verge",
    "published": "2026-02-17T15:30:04+00:00"
  },
  {
    "title": "Legal challenge to Met's Freemasons policy thrown out",
    "link": "https://www.bbc.com/news/articles/cly86125nqno?at_medium=RSS&at_campaign=rss",
    "source": "BBC News",
    "published": "2026-02-17T15:20:00+00:00"
  },
  {
    "title": "Ashraf Reza appointed PM\u2019s personal secretary",
    "link": "https://www.tbsnews.net/bangladesh/ashraf-reza-appointed-pms-personal-secretary-1364446",
    "source": "The Business Standard",
    "published": "2026-02-17T15:15:00+00:00"
  },
  {
    "title": "Viral face depuffing tricks - skin experts reveal if they work",
    "link": "https://www.bbc.com/news/articles/ce8wd6pzl72o?at_medium=RSS&at_campaign=rss",
    "source": "BBC News",
    "published": "2026-02-17T15:14:28+00:00"
  },
  {
    "title": "New Sign at Bridge to Canada Aims to Keep Immigrant Drivers Out of Trap",
    "link": "https://www.nytimes.com/2026/02/17/nyregion/peace-bridge-immigration.html",
    "source": "New York Times",
    "published": "2026-02-17T15:12:17+00:00"
  },
  {
    "title": "Shein\u2019s \u2018addictive design\u2019 and illegal sex dolls under investigation",
    "link": "https://www.theverge.com/policy/879964/shein-eu-dsa-investigation-illegal-products-addictive-design",
    "source": "The Verge",
    "published": "2026-02-17T15:10:23+00:00"
  },
  {
    "title": "Ex-priest receives second lifetime ban for child sexual abuse",
    "link": "https://www.bbc.com/news/articles/c0e5gdvj719o?at_medium=RSS&at_campaign=rss",
    "source": "BBC News",
    "published": "2026-02-17T15:10:16+00:00"
  },
  {
    "title": "Tarique Rahman meets foreign dignitaries after taking oath as PM",
    "link": "https://www.tbsnews.net/bangladesh/tarique-rahman-meets-foreign-dignitaries-after-taking-oath-pm-1364481",
    "source": "The Business Standard",
    "published": "2026-02-17T15:05:00+00:00"
  },
  {
    "title": "Toyota fills out its skimpy EV lineup with the bZ Woodland SUV",
    "link": "https://www.theverge.com/transportation/878849/toyota-bz-woodland-specs-price-ev-offroad",
    "source": "The Verge",
    "published": "2026-02-17T15:00:00+00:00"
  },
  {
    "title": "Vegetables become costlier two days before Ramadan; Zahidi date prices nearly double",
    "link": "https://www.tbsnews.net/economy/bazaar/vegetable-prices-surge-ramadan-nears-low-income-date-prices-nearly-double-1364401",
    "source": "The Business Standard",
    "published": "2026-02-17T14:55:00+00:00"
  },
  {
    "title": "Jesse Jackson, Charismatic Champion of Civil Rights, Dies at 84",
    "link": "https://www.nytimes.com/2026/02/17/us/jesse-jackson-dead.html",
    "source": "New York Times",
    "published": "2026-02-17T14:38:41+00:00"
  },
  {
    "title": "Hegseth Is Said to Have Ordered Pentagon Spokesman\u2019s Firing",
    "link": "https://www.nytimes.com/2026/02/17/us/politics/hegseth-pentagon-spokesman-fired.html",
    "source": "New York Times",
    "published": "2026-02-17T14:23:51+00:00"
  },
  {
    "title": "The man whose bad break-up gave Madonna her breakthrough hit Like A Virgin",
    "link": "https://www.bbc.com/news/articles/cvgveqzld59o?at_medium=RSS&at_campaign=rss",
    "source": "BBC News",
    "published": "2026-02-17T14:22:12+00:00"
  },
  {
    "title": "Nuclear talks between US and Iran end in Geneva",
    "link": "https://www.bbc.com/news/articles/cwyknjnd706o?at_medium=RSS&at_campaign=rss",
    "source": "BBC News",
    "published": "2026-02-17T14:21:23+00:00"
  },
  {
    "title": "France releases suspected Russian 'shadow fleet' tanker after fine paid",
    "link": "https://www.bbc.com/news/articles/c8xy4dl2xwgo?at_medium=RSS&at_campaign=rss",
    "source": "BBC News",
    "published": "2026-02-17T14:20:33+00:00"
  },
  {
    "title": "Warner Bros. Discovery Restarts Deal Talks With Paramount",
    "link": "https://www.nytimes.com/2026/02/17/business/warner-bros-discovery-paramount.html",
    "source": "New York Times",
    "published": "2026-02-17T14:01:46+00:00"
  },
  {
    "title": "Winners of the 2026 Sony World Photography Awards Open Competition",
    "link": "https://www.theatlantic.com/photography/2026/02/winners-2026-sony-world-photography-awards-open-competition/686022/?utm_source=feed",
    "source": "The Atlantic",
    "published": "2026-02-17T14:00:00+00:00"
  },
  {
    "title": "Peak Design has wearable gadget straps for people who hate bags",
    "link": "https://www.theverge.com/tech/879908/peak-design-crossbody-phone-strap-launch-price",
    "source": "The Verge",
    "published": "2026-02-17T14:00:00+00:00"
  },
  {
    "title": "Warner Bros. Discovery gives Paramount one week to present its \u2018best and final\u2019 offer",
    "link": "https://www.theverge.com/entertainment/879947/warner-bros-discovery-reopen-talks-paramount-netflix-merger",
    "source": "The Verge",
    "published": "2026-02-17T13:56:34+00:00"
  },
  {
    "title": "USA's Meyers Taylor, 41, becomes oldest individual Olympic champion at a Winter Games",
    "link": "https://www.bbc.com/sport/articles/cpv84182rp2o?at_medium=RSS&at_campaign=rss",
    "source": "BBC News",
    "published": "2026-02-17T13:00:40+00:00"
  },
  {
    "title": "The Republicans Made Peace With Science",
    "link": "https://www.theatlantic.com/ideas/2026/02/republicans-democrats-science-funding-trump/685996/?utm_source=feed",
    "source": "The Atlantic",
    "published": "2026-02-17T13:00:00+00:00"
  },
  {
    "title": "Laurie Spiegel on the difference between algorithmic music and \u2018AI\u2019",
    "link": "https://www.theverge.com/report/879819/laurie-spiegel-is-celebrating-40-of-music-mouse-with-a-modern-revival",
    "source": "The Verge",
    "published": "2026-02-17T13:00:00+00:00"
  },
  {
    "title": "Obama Took On Recession, Health Care and Iraq. What He Didn\u2019t See Coming Was Trump.",
    "link": "https://www.nytimes.com/2026/02/17/us/politics/obama-trump-oral-history.html",
    "source": "New York Times",
    "published": "2026-02-17T12:57:55+00:00"
  },
  {
    "title": "New Jersey Commuters Face Month of Misery as Service to Manhattan Is Slashed",
    "link": "https://www.nytimes.com/2026/02/17/nyregion/new-jersey-transit-delays-manhattan.html",
    "source": "New York Times",
    "published": "2026-02-17T12:56:43+00:00"
  },
  {
    "title": "Watch: Key moments that defined Jesse Jackson's life",
    "link": "https://www.bbc.com/news/videos/cvg4y9ee16go?at_medium=RSS&at_campaign=rss",
    "source": "BBC News",
    "published": "2026-02-17T12:52:08+00:00"
  },
  {
    "title": "Italian toddler critical after undergoing heart transplant with organ damaged 'by frostbite'",
    "link": "https://www.bbc.com/news/articles/cpqw24v4dn9o?at_medium=RSS&at_campaign=rss",
    "source": "BBC News",
    "published": "2026-02-17T12:43:57+00:00"
  },
  {
    "title": "India has long promised 'vibrant' border villages, as China speedily builds up",
    "link": "https://www.npr.org/2026/02/17/nx-s1-5702816/india-china-border-villages-development",
    "source": "NPR",
    "published": "2026-02-17T12:30:00+00:00"
  },
  {
    "title": "Shop owners in Northern Ireland fear violence after paramilitaries demand protection money",
    "link": "https://www.bbc.com/news/articles/c20znn792g1o?at_medium=RSS&at_campaign=rss",
    "source": "BBC News",
    "published": "2026-02-17T12:21:15+00:00"
  },
  {
    "title": "Cold health alert issued as temperatures fall across the UK",
    "link": "https://www.bbc.com/news/articles/cdxgew324r9o?at_medium=RSS&at_campaign=rss",
    "source": "BBC News",
    "published": "2026-02-17T12:06:53+00:00"
  },
  {
    "title": "Rev. Jesse Jackson has died. And, U.S. and Iran set for high-stakes nuclear talks",
    "link": "https://www.npr.org/2026/02/17/g-s1-110385/up-first-newsletter-iran-geneva-ice-shooting-texas-trial-jesse-jackson-alex-pretti",
    "source": "NPR",
    "published": "2026-02-17T12:04:37+00:00"
  },
  {
    "title": "Europe Has Received the Message",
    "link": "https://www.theatlantic.com/international/2026/02/european-union-defense-spending/685983/?utm_source=feed",
    "source": "The Atlantic",
    "published": "2026-02-17T12:00:00+00:00"
  },
  {
    "title": "American Kids Used to Eat Everything",
    "link": "https://www.theatlantic.com/family/2026/02/picky-american-kids-food/685956/?utm_source=feed",
    "source": "The Atlantic",
    "published": "2026-02-17T12:00:00+00:00"
  },
  {
    "title": "Seeing Ourselves in America\u2019s Unfinished Revolution",
    "link": "https://www.theatlantic.com/magazine/2026/03/the-commons/685765/?utm_source=feed",
    "source": "The Atlantic",
    "published": "2026-02-17T12:00:00+00:00"
  },
  {
    "title": "The Ghosts of Toni Morrison",
    "link": "https://www.theatlantic.com/magazine/2026/03/toni-morrison-black-american-history/685761/?utm_source=feed",
    "source": "The Atlantic",
    "published": "2026-02-17T12:00:00+00:00"
  },
  {
    "title": "Boy first in UK to have pioneering leg-lengthening surgery",
    "link": "https://www.bbc.com/news/articles/cgqg92ll8vqo?at_medium=RSS&at_campaign=rss",
    "source": "BBC News",
    "published": "2026-02-17T11:32:08+00:00"
  },
  {
    "title": "The record-breaking cocaine boom \u2014 and its deadly fallout",
    "link": "https://www.npr.org/sections/planet-money/2026/02/17/g-s1-110042/the-record-breaking-cocaine-boom-and-its-deadly-fallout",
    "source": "NPR",
    "published": "2026-02-17T11:30:00+00:00"
  },
  {
    "title": "No, It\u2019s Not Back to Business as Usual",
    "link": "https://www.theatlantic.com/ideas/2026/02/for-europe-its-not-back-to-business-as-usual/686023/?utm_source=feed",
    "source": "The Atlantic",
    "published": "2026-02-17T11:27:47+00:00"
  },
  {
    "title": "Marco Rubio\u2019s Impressive Speech",
    "link": "https://www.theatlantic.com/ideas/2026/02/marco-rubio-munich/686025/?utm_source=feed",
    "source": "The Atlantic",
    "published": "2026-02-17T11:00:00+00:00"
  },
  {
    "title": "Lindsey Vonn 'yet to stand' but returns home to US",
    "link": "https://www.bbc.com/sport/articles/c62gx5wl92wo?at_medium=RSS&at_campaign=rss",
    "source": "BBC News",
    "published": "2026-02-17T10:57:20+00:00"
  },
  {
    "title": "Longtime civil rights leader the Rev. Jesse Jackson dies at 84",
    "link": "https://www.npr.org/2026/02/17/963124454/jesse-jackson-civil-rights-leader-rainbow-coalition-dies",
    "source": "NPR",
    "published": "2026-02-17T10:34:32+00:00"
  },
  {
    "title": "A big day for GB's men's curling team - Tuesday's guide",
    "link": "https://www.bbc.com/sport/articles/c338y36kngzo?at_medium=RSS&at_campaign=rss",
    "source": "BBC News",
    "published": "2026-02-17T10:28:35+00:00"
  },
  {
    "title": "Jesse Jackson: A Life in Pictures",
    "link": "https://www.nytimes.com/2026/02/17/us/politics/jesse-jackson-photos.html",
    "source": "New York Times",
    "published": "2026-02-17T10:12:57+00:00"
  },
  {
    "title": "Robert Duvall Seared Himself Into Our Memories Even When He Wasn\u2019t the Star",
    "link": "https://www.nytimes.com/2026/02/17/movies/robert-duvall-the-godfather-to-kill-a-mockingbird.html",
    "source": "New York Times",
    "published": "2026-02-17T10:03:24+00:00"
  },
  {
    "title": "Trump Sought Vast Budget Cuts. Congress Granted Few.",
    "link": "https://www.nytimes.com/2026/02/17/us/politics/trump-congress-budget-cuts.html",
    "source": "New York Times",
    "published": "2026-02-17T10:03:00+00:00"
  },
  {
    "title": "Military Veterans Are Among Americans Protesting ICE",
    "link": "https://www.nytimes.com/2026/02/17/us/minnesota-immigration-protest-veterans.html",
    "source": "New York Times",
    "published": "2026-02-17T10:02:44+00:00"
  },
  {
    "title": "Daniel Radcliffe on Returning to Broadway in \u2018Every Brilliant Thing\u2019",
    "link": "https://www.nytimes.com/2026/02/17/theater/daniel-radcliffe-every-brilliant-thing.html",
    "source": "New York Times",
    "published": "2026-02-17T10:02:20+00:00"
  },
  {
    "title": "Chatbots Are the New Influencers Brands Must Woo",
    "link": "https://www.nytimes.com/2026/02/17/technology/chatbots-influencers-brands-marketing.html",
    "source": "New York Times",
    "published": "2026-02-17T10:02:10+00:00"
  },
  {
    "title": "Did That Bald Head Get Your Attention? One Start-Up Hopes So.",
    "link": "https://www.nytimes.com/2026/02/17/technology/did-that-bald-head-get-your-attention-one-start-up-hopes-so.html",
    "source": "New York Times",
    "published": "2026-02-17T10:01:00+00:00"
  },
  {
    "title": "Minnesota Republicans defend their focus on fraud despite the ICE surge that followed",
    "link": "https://www.npr.org/2026/02/17/nx-s1-5716113/minnesota-nick-shirley-fraud-ice-minneapolis",
    "source": "NPR",
    "published": "2026-02-17T10:00:00+00:00"
  },
  {
    "title": "This behavior can be a turning point for families caring for a dementia patient",
    "link": "https://www.npr.org/2026/02/17/nx-s1-5715970/dementia-alzheimers-elopement-lost-memory-care",
    "source": "NPR",
    "published": "2026-02-17T10:00:00+00:00"
  },
  {
    "title": "Immigration crackdown in Maine is a top issue in battle for key Senate seat",
    "link": "https://www.npr.org/2026/02/17/nx-s1-5713854/immigration-crackdown-maine-top-issue-battle-key-senate-seat",
    "source": "NPR",
    "published": "2026-02-17T10:00:00+00:00"
  },
  {
    "title": "3 big changes are proposed for FEMA. This is what experts really think of them",
    "link": "https://www.npr.org/2026/02/17/nx-s1-5698320/fema-reform-trump-hurricane-earthquake",
    "source": "NPR",
    "published": "2026-02-17T10:00:00+00:00"
  },
  {
    "title": "TV antennas and Super Bowl rehearsals: How prediction market traders seek an edge",
    "link": "https://www.npr.org/2026/02/17/nx-s1-5716224/kalshi-polymarket-super-bowl-alpha",
    "source": "NPR",
    "published": "2026-02-17T10:00:00+00:00"
  },
  {
    "title": "Adoption breakdown ended my career and relationship \u2013 we're told to get on with it",
    "link": "https://www.bbc.com/news/articles/czj1708v1ejo?at_medium=RSS&at_campaign=rss",
    "source": "BBC News",
    "published": "2026-02-17T09:58:13+00:00"
  },
  {
    "title": "Trump Said He\u2019d End the War in Ukraine in a Day. It\u2019s Harder Than He Thought.",
    "link": "https://www.nytimes.com/2026/02/17/world/europe/trump-ukraine-war-putin.html",
    "source": "New York Times",
    "published": "2026-02-17T09:25:31+00:00"
  },
  {
    "title": "'The Michael Jackson of curling': Glaswegian, 61, whose ice rink moonwalk went viral",
    "link": "https://www.bbc.com/sport/articles/c6263m1m807o?at_medium=RSS&at_campaign=rss",
    "source": "BBC News",
    "published": "2026-02-17T08:00:19+00:00"
  },
  {
    "title": "How will freeze on tax thresholds affect your take-home pay? Use our calculator",
    "link": "https://www.bbc.com/news/articles/c99k7djlklyo?at_medium=RSS&at_campaign=rss",
    "source": "BBC News",
    "published": "2026-02-17T07:10:15+00:00"
  },
  {
    "title": "Colbert Doesn\u2019t Give an FCC About Calling Out CBS",
    "link": "https://www.nytimes.com/2026/02/17/arts/television/colbert-fcc-trump-talarico-cbs.html",
    "source": "New York Times",
    "published": "2026-02-17T06:46:58+00:00"
  },
  {
    "title": "Patients describe 'culture of abuse' as 15 hospital staff arrested",
    "link": "https://www.bbc.com/news/articles/c5y4nyxwd7eo?at_medium=RSS&at_campaign=rss",
    "source": "BBC News",
    "published": "2026-02-17T05:14:52+00:00"
  },
  {
    "title": "Height Surgery for Men Can Add Inches But Has Risks",
    "link": "https://www.nytimes.com/2026/02/17/us/height-surgery-limb-lengthening-men-health.html",
    "source": "New York Times",
    "published": "2026-02-17T05:01:12+00:00"
  },
  {
    "title": "After Trip to Germany, AOC Expresses Frustrations",
    "link": "https://www.nytimes.com/2026/02/16/us/politics/aoc-germany-munich-security-conference.html",
    "source": "New York Times",
    "published": "2026-02-17T01:33:49+00:00"
  },
  {
    "title": "Reddit's human content wins amid the AI flood",
    "link": "https://www.bbc.com/news/articles/c5y4zl0w062o?at_medium=RSS&at_campaign=rss",
    "source": "BBC News",
    "published": "2026-02-17T00:03:10+00:00"
  },
  {
    "title": "A Different Kind of Leading Man",
    "link": "https://www.theatlantic.com/culture/2026/02/robert-duvall-appreciation-mockingbird-godfather/686024/?utm_source=feed",
    "source": "The Atlantic",
    "published": "2026-02-16T23:01:00+00:00"
  },
  {
    "title": "How dark web agent spotted bedroom wall clue to rescue girl from years of harm",
    "link": "https://www.bbc.com/news/articles/cx2gn239exlo?at_medium=RSS&at_campaign=rss",
    "source": "BBC News",
    "published": "2026-02-16T22:02:33+00:00"
  },
  {
    "title": "Winter Olympics Photo of the Day: Snow Jump",
    "link": "https://www.theatlantic.com/photography/2026/02/winter-olympics-photo-day-snow-jump/686021/?utm_source=feed",
    "source": "The Atlantic",
    "published": "2026-02-16T21:15:39+00:00"
  }
]