[
  {
    "title": "'That's me!': Hundreds tell BBC how medication triggered gambling and other addictions",
    "link": "https://www.bbc.com/news/articles/ce948d9gxevo?at_medium=RSS&at_campaign=rss",
    "source": "BBC News",
    "published": "2026-02-21T07:12:03+00:00"
  },
  {
    "title": "PM releases commemorative postage stamp on Int\u2019l Mother Language Day",
    "link": "https://www.tbsnews.net/bangladesh/pm-releases-commemorative-postage-stamp-intl-mother-language-day-1367356",
    "source": "The Business Standard",
    "published": "2026-02-21T06:50:00+00:00"
  },
  {
    "title": "Tarique Rahman begins work at PMO",
    "link": "https://www.tbsnews.net/bangladesh/pm-tarique-begins-work-tejgaon-pmo-1367321",
    "source": "The Business Standard",
    "published": "2026-02-21T06:40:00+00:00"
  },
  {
    "title": "Dhaka gets almost half of total remittances earnings in H1 of FY26",
    "link": "https://www.tbsnews.net/infograph/numbers/dhaka-division-gets-almost-half-total-remittances-earnings-h1-fy26-1367326",
    "source": "The Business Standard",
    "published": "2026-02-21T06:40:00+00:00"
  },
  {
    "title": "After the Supreme Court's ruling on tariffs, companies line up for refunds",
    "link": "https://www.npr.org/2026/02/21/g-s1-110987/supreme-court-tariffs-refunds",
    "source": "NPR",
    "published": "2026-02-21T06:18:50+00:00"
  },
  {
    "title": "Why fake AI videos of UK urban decline are taking over social media",
    "link": "https://www.bbc.com/news/articles/c4g8r23yv71o?at_medium=RSS&at_campaign=rss",
    "source": "BBC News",
    "published": "2026-02-21T06:04:41+00:00"
  },
  {
    "title": "3 killed as pickup collides with autorickshaw in Moulvibazar",
    "link": "https://www.tbsnews.net/bangladesh/3-killed-pickup-collides-autorickshaw-moulvibazar-1367251",
    "source": "The Business Standard",
    "published": "2026-02-21T05:45:00+00:00"
  },
  {
    "title": "What Bangladesh can learn from Sri Lanka's debt crisis",
    "link": "https://www.tbsnews.net/economy/what-bangladesh-can-learn-sri-lankas-debt-crisis-1367246",
    "source": "The Business Standard",
    "published": "2026-02-21T05:20:00+00:00"
  },
  {
    "title": "Gis\u00e8le Pelicot Survived Mass Rape. Now She\u2019s Looking to the Future.",
    "link": "https://www.nytimes.com/2026/02/21/gisele-pelicot-interview-hymn-to-life.html",
    "source": "New York Times",
    "published": "2026-02-21T05:01:07+00:00"
  },
  {
    "title": "Government considers removing Andrew from royal line of succession",
    "link": "https://www.bbc.com/news/articles/c1kgv837wvdo?at_medium=RSS&at_campaign=rss",
    "source": "BBC News",
    "published": "2026-02-21T04:45:25+00:00"
  },
  {
    "title": "Bridge Owner Donated $1 Million to MAGA Group Before Trump Blasted Competitor",
    "link": "https://www.nytimes.com/2026/02/20/us/politics/trump-canada-bridge-maga-inc-donation.html",
    "source": "New York Times",
    "published": "2026-02-21T04:45:02+00:00"
  },
  {
    "title": "Revenue lags, costly mega projects raise external debt risks",
    "link": "https://www.tbsnews.net/economy/revenue-lags-costly-mega-projects-raise-external-debt-risks-1367161",
    "source": "The Business Standard",
    "published": "2026-02-21T04:30:00+00:00"
  },
  {
    "title": "Multi-cancer blood test missed key goal in NHS trial",
    "link": "https://www.bbc.com/news/articles/cwyx7580xvyo?at_medium=RSS&at_campaign=rss",
    "source": "BBC News",
    "published": "2026-02-21T04:23:11+00:00"
  },
  {
    "title": "Nation remembers language heroes",
    "link": "https://www.tbsnews.net/bangladesh/nation-remembers-language-heroes-1367201",
    "source": "The Business Standard",
    "published": "2026-02-21T04:10:00+00:00"
  },
  {
    "title": "After Supreme Court Loss, Trump Plans to Impose Global Tariffs Using Different Laws",
    "link": "https://www.nytimes.com/2026/02/20/us/politics/trump-tariffs-plans.html",
    "source": "New York Times",
    "published": "2026-02-21T03:58:10+00:00"
  },
  {
    "title": "Whitewashing \u2018Wuthering Heights\u2019",
    "link": "https://www.nytimes.com/2026/02/20/opinion/wuthering-heights-jacob-elordi-bridgerton.html",
    "source": "New York Times",
    "published": "2026-02-21T03:51:28+00:00"
  },
  {
    "title": "A new dawn interrupted by an old shadow",
    "link": "https://www.tbsnews.net/analysis/new-dawn-interrupted-old-shadow-1367131",
    "source": "The Business Standard",
    "published": "2026-02-21T03:00:00+00:00"
  },
  {
    "title": "L.G.B.T.Q. Clubs in Some Texas Schools Can\u2019t Be Banned, Judge Says",
    "link": "https://www.nytimes.com/2026/02/20/us/texas-ban-lgbtq-clubs.html",
    "source": "New York Times",
    "published": "2026-02-21T02:38:54+00:00"
  },
  {
    "title": "Modi congratulates Bangladesh's new prime minister, stresses 'inclusive' governance",
    "link": "https://www.tbsnews.net/world/south-asia/modi-congratulates-bangladeshs-new-prime-minister-stresses-inclusive-governance",
    "source": "The Business Standard",
    "published": "2026-02-21T02:25:00+00:00"
  },
  {
    "title": "I might not get uni Covid compensation - but I'm claiming it out of principle",
    "link": "https://www.bbc.com/news/articles/cp81j7n2271o?at_medium=RSS&at_campaign=rss",
    "source": "BBC News",
    "published": "2026-02-21T02:17:46+00:00"
  },
  {
    "title": "Ekushey now free, opens path to democratic Bangladesh: Fakhrul",
    "link": "https://www.tbsnews.net/bangladesh/ekushey-now-free-opens-path-democratic-bangladesh-fakhrul-1367136",
    "source": "The Business Standard",
    "published": "2026-02-21T02:15:00+00:00"
  },
  {
    "title": "The government is reforming the SEND system. This is what those impacted want changing",
    "link": "https://www.bbc.com/news/articles/c2e4rvzw7nlo?at_medium=RSS&at_campaign=rss",
    "source": "BBC News",
    "published": "2026-02-21T02:05:13+00:00"
  },
  {
    "title": "Police Chief Placed Millions in Bets as He Embezzled, Investigators Say",
    "link": "https://www.nytimes.com/2026/02/20/nyregion/new-haven-police-chief-gambling-embezzle.html",
    "source": "New York Times",
    "published": "2026-02-21T02:01:07+00:00"
  },
  {
    "title": "How Co-op Live went from falling air con units to hosting the Brits",
    "link": "https://www.bbc.com/news/articles/cwy67q6pkpwo?at_medium=RSS&at_campaign=rss",
    "source": "BBC News",
    "published": "2026-02-21T01:58:28+00:00"
  },
  {
    "title": "Even After Supreme Court Ruling, Trump Insists He Can Do as He Wishes",
    "link": "https://www.nytimes.com/2026/02/20/us/politics/trump-justices-gorsuch-barrett-roberts.html",
    "source": "New York Times",
    "published": "2026-02-21T01:52:29+00:00"
  },
  {
    "title": "Trump brings in new 10% tariff as Supreme Court rejects his global import taxes",
    "link": "https://www.bbc.com/news/articles/cn8146l0n55o?at_medium=RSS&at_campaign=rss",
    "source": "BBC News",
    "published": "2026-02-21T01:43:05+00:00"
  },
  {
    "title": "Longtime Virginia Lawyer Chosen by Judges as U.S. Attorney, and Then Fired",
    "link": "https://www.nytimes.com/2026/02/20/us/politics/us-attorney-eastern-district-of-virginia.html",
    "source": "New York Times",
    "published": "2026-02-21T01:36:24+00:00"
  },
  {
    "title": "Is \u00a370 becoming harder to justify? The rise of cheaper blockbuster games",
    "link": "https://www.bbc.com/news/articles/ckg1nwwv1xyo?at_medium=RSS&at_campaign=rss",
    "source": "BBC News",
    "published": "2026-02-21T01:30:31+00:00"
  },
  {
    "title": "Court Clears Way for Louisiana Law Requiring Ten Commandments in Classrooms",
    "link": "https://www.nytimes.com/2026/02/20/us/louisiana-classrooms-ten-commandments.html",
    "source": "New York Times",
    "published": "2026-02-21T01:30:23+00:00"
  },
  {
    "title": "UK puffins in peril as winter storms threaten mass seabird 'wreck'",
    "link": "https://www.bbc.com/news/articles/c043edkn942o?at_medium=RSS&at_campaign=rss",
    "source": "BBC News",
    "published": "2026-02-21T01:21:00+00:00"
  },
  {
    "title": "The best looks at London Fashion Week 2026",
    "link": "https://www.bbc.com/news/articles/c4g0ke64v3no?at_medium=RSS&at_campaign=rss",
    "source": "BBC News",
    "published": "2026-02-21T01:00:07+00:00"
  },
  {
    "title": "With Tariff Changes, Consumers May Be Stuck in a Waiting Game",
    "link": "https://www.nytimes.com/2026/02/20/business/economy/tariff-ruling-consumer-prices.html",
    "source": "New York Times",
    "published": "2026-02-21T00:52:46+00:00"
  },
  {
    "title": "Iran's motorcycling midwife and rights campaigner is star of Oscar-tipped film",
    "link": "https://www.bbc.com/news/articles/cn0ewenyg22o?at_medium=RSS&at_campaign=rss",
    "source": "BBC News",
    "published": "2026-02-21T00:44:24+00:00"
  },
  {
    "title": "Killing of nationalist student leaves French far left in deep trouble as elections loom",
    "link": "https://www.bbc.com/news/articles/cnv61zv534eo?at_medium=RSS&at_campaign=rss",
    "source": "BBC News",
    "published": "2026-02-21T00:32:16+00:00"
  },
  {
    "title": "In the army now: Pictures that show how ordinary Ukrainians have been shaped by war",
    "link": "https://www.bbc.com/news/articles/cddn2e11zm8o?at_medium=RSS&at_campaign=rss",
    "source": "BBC News",
    "published": "2026-02-21T00:22:28+00:00"
  },
  {
    "title": "Bench Presses, Pull Ups \u2026 Kid Rock? The White House Had a Very Manly Week.",
    "link": "https://www.nytimes.com/2026/02/20/us/politics/trump-hegseth-rfk-manliness.html",
    "source": "New York Times",
    "published": "2026-02-21T00:10:49+00:00"
  },
  {
    "title": "U.S. Planes Land at Jordan Base, a Key Hub for Planning Possible Iran Strikes",
    "link": "https://www.nytimes.com/2026/02/20/us/politics/us-military-jordan-iran.html",
    "source": "New York Times",
    "published": "2026-02-21T00:04:46+00:00"
  },
  {
    "title": "Puberty blockers trial paused over concerns from medicines watchdog",
    "link": "https://www.bbc.com/news/articles/cjd9z0p27k5o?at_medium=RSS&at_campaign=rss",
    "source": "BBC News",
    "published": "2026-02-20T23:36:23+00:00"
  },
  {
    "title": "Ruben Ray Martinez Was Killed in an Undisclosed ICE Shooting in March, His Family Says",
    "link": "https://www.nytimes.com/2026/02/20/us/ruben-ray-martinez-ice-shooting-texas.html",
    "source": "New York Times",
    "published": "2026-02-20T23:26:10+00:00"
  },
  {
    "title": "C.I.A. Retracts Reports Flagged for Bias",
    "link": "https://www.nytimes.com/2026/02/20/us/politics/cia-retracts-reports.html",
    "source": "New York Times",
    "published": "2026-02-20T23:23:56+00:00"
  },
  {
    "title": "Another Winter Storm Could Deliver More Snow to the Northeast This Weekend",
    "link": "https://www.nytimes.com/2026/02/20/weather/new-york-snow-forecast.html",
    "source": "New York Times",
    "published": "2026-02-20T22:44:30+00:00"
  },
  {
    "title": "Trump says he is considering limited military strike on Iran",
    "link": "https://www.bbc.com/news/articles/cdxzk4gvzp0o?at_medium=RSS&at_campaign=rss",
    "source": "BBC News",
    "published": "2026-02-20T22:38:45+00:00"
  },
  {
    "title": "The best e-reader to buy right now",
    "link": "https://www.theverge.com/23769068/best-ebook-readers",
    "source": "The Verge",
    "published": "2026-02-20T22:19:29+00:00"
  },
  {
    "title": "Welcome to Australia's hottest beach event - nowhere near the sea",
    "link": "https://www.bbc.com/news/articles/crrx792qk81o?at_medium=RSS&at_campaign=rss",
    "source": "BBC News",
    "published": "2026-02-20T22:16:49+00:00"
  },
  {
    "title": "In Berlin, there are movies, there's politics and there's talk about it all",
    "link": "https://www.npr.org/2026/02/20/nx-s1-5713927/berlin-film-festival-gaza-politics",
    "source": "NPR",
    "published": "2026-02-20T22:01:51+00:00"
  },
  {
    "title": "Christopher S. Wren, Times Bureau Chief in Hostile Lands, Dies at 89",
    "link": "https://www.nytimes.com/2026/02/20/business/media/christopher-wren-dead.html",
    "source": "New York Times",
    "published": "2026-02-20T21:55:52+00:00"
  },
  {
    "title": "GB go for men's curling gold and Atkin in halfpipe final - Saturday's guide",
    "link": "https://www.bbc.com/sport/articles/c338y36kngzo?at_medium=RSS&at_campaign=rss",
    "source": "BBC News",
    "published": "2026-02-20T21:54:34+00:00"
  },
  {
    "title": "Xbox shakeup: Phil Spencer and Sarah Bond are leaving Microsoft",
    "link": "https://www.theverge.com/games/882363/xbox-microsoft-phil-spencer-out",
    "source": "The Verge",
    "published": "2026-02-20T21:29:01+00:00"
  },
  {
    "title": "Alex Ferreira wins 10th gold medal for Team USA, matching America's highest total in Winter Olympics",
    "link": "https://www.npr.org/2026/02/20/nx-s1-5721177/alex-ferreira-wins-10th-gold-medal-for-team-usa-matching-most-ever-in-winter-olympics",
    "source": "NPR",
    "published": "2026-02-20T21:18:10+00:00"
  },
  {
    "title": "'I'm on right side' - Team GB's Kenworthy on death threats after ICE post",
    "link": "https://www.bbc.com/sport/articles/c07j18rgrpxo?at_medium=RSS&at_campaign=rss",
    "source": "BBC News",
    "published": "2026-02-20T21:03:41+00:00"
  },
  {
    "title": "Microsoft says today\u2019s Xbox shake-up doesn\u2019t mean game studio layoffs",
    "link": "https://www.theverge.com/games/882377/microsoft-says-todays-xbox-shakeup-doesnt-mean-game-studio-layoffs",
    "source": "The Verge",
    "published": "2026-02-20T20:58:27+00:00"
  },
  {
    "title": "Hungary Poses Unexpected Hurdle to Europe\u2019s 90-Billion Euro Loan to Ukraine",
    "link": "https://www.nytimes.com/2026/02/20/world/europe/euro-loan-ukraine-hungary-obstacle.html",
    "source": "New York Times",
    "published": "2026-02-20T20:56:32+00:00"
  },
  {
    "title": "SCOTUS rules Trump\u2019s tariffs are illegal \u2014 but the fight is far from over",
    "link": "https://www.theverge.com/policy/882227/scotus-trump-tariffs-ruling-imports-small-businesses-refunds",
    "source": "The Verge",
    "published": "2026-02-20T20:45:44+00:00"
  },
  {
    "title": "The Supreme Court Isn\u2019t a Rubber Stamp",
    "link": "https://www.theatlantic.com/ideas/2026/02/scotus-tariff-decision-trump/686087/?utm_source=feed",
    "source": "The Atlantic",
    "published": "2026-02-20T20:35:23+00:00"
  },
  {
    "title": "Will the Supreme Court\u2019s Tariff Ruling Curb Trump?",
    "link": "https://www.nytimes.com/2026/02/20/opinion/trump-tariffs-supreme-court.html",
    "source": "New York Times",
    "published": "2026-02-20T20:31:00+00:00"
  },
  {
    "title": "Read Microsoft gaming CEO Asha Sharma&#8217;s first memo on the future of Xbox",
    "link": "https://www.theverge.com/games/882326/read-microsoft-gaming-ceo-asha-sharma-first-memo",
    "source": "The Verge",
    "published": "2026-02-20T20:30:59+00:00"
  },
  {
    "title": "Read Xbox chief Phil Spencer\u2019s memo about leaving Microsoft",
    "link": "https://www.theverge.com/news/882340/xbox-phil-spencer-microsoft-retirement-memo",
    "source": "The Verge",
    "published": "2026-02-20T20:30:16+00:00"
  },
  {
    "title": "Xbox chief Phil Spencer is leaving Microsoft",
    "link": "https://www.theverge.com/news/882241/microsoft-phil-spencer-xbox-leaving-retirement",
    "source": "The Verge",
    "published": "2026-02-20T20:30:04+00:00"
  },
  {
    "title": "Sarah Bond is leaving Xbox",
    "link": "https://www.theverge.com/games/882281/xbox-sarah-bond-leaving-microsoft",
    "source": "The Verge",
    "published": "2026-02-20T20:29:44+00:00"
  },
  {
    "title": "Winter Olympics Photo of the Day: Shredding the Halfpipe",
    "link": "https://www.theatlantic.com/photography/2026/02/winter-olympics-photo-day-shredding-halfpipe/686088/?utm_source=feed",
    "source": "The Atlantic",
    "published": "2026-02-20T20:25:41+00:00"
  },
  {
    "title": "Trump is making coal plants even dirtier as AI demands more energy",
    "link": "https://www.theverge.com/science/882288/trump-ai-data-center-power-plant-pollution-mercury-mats",
    "source": "The Verge",
    "published": "2026-02-20T20:18:34+00:00"
  },
  {
    "title": "Web scraper sued by Google claims Google is the one scraping the web",
    "link": "https://www.theverge.com/tech/882300/serpapi-google-lawsuit-web-scraper-motion-to-dismiss",
    "source": "The Verge",
    "published": "2026-02-20T20:06:46+00:00"
  },
  {
    "title": "Today\u2019s <em>Atlantic </em>Trivia: Mythical Geography",
    "link": "https://www.theatlantic.com/newsletters/2026/02/daily-trivia-questions-answers-week-18/686039/?utm_source=feed",
    "source": "The Atlantic",
    "published": "2026-02-20T20:00:00+00:00"
  },
  {
    "title": "Former Prince Andrew\u2019s Arrest Upends Royal Family\u2019s Effort to Move Past His Scandal",
    "link": "https://www.nytimes.com/2026/02/20/world/europe/prince-andrew-arrest-epstein-royal-family-uk.html",
    "source": "New York Times",
    "published": "2026-02-20T19:56:29+00:00"
  },
  {
    "title": "San Jos\u00e9 State University Graduate Is Found Dead in Tree Well at Lake Tahoe Resort",
    "link": "https://www.nytimes.com/2026/02/20/us/san-jose-state-skier-dead.html",
    "source": "New York Times",
    "published": "2026-02-20T19:45:52+00:00"
  },
  {
    "title": "Dog Poop Wars: In New York, the Snow Is Foul, and So Is the Discourse",
    "link": "https://www.nytimes.com/2026/02/20/nyregion/new-york-snow-dog-waste.html",
    "source": "New York Times",
    "published": "2026-02-20T19:40:37+00:00"
  },
  {
    "title": "GB '25 years' behind world's best in short track",
    "link": "https://www.bbc.com/sport/articles/czx70wpxkp1o?at_medium=RSS&at_campaign=rss",
    "source": "BBC News",
    "published": "2026-02-20T19:34:00+00:00"
  },
  {
    "title": "Trump calls SCOTUS tariffs decision 'deeply disappointing' and lays out path forward",
    "link": "https://www.npr.org/2026/02/20/nx-s1-5720826/trump-calls-scotus-tariffs-decision-deeply-disappointing-and-lays-out-path-forward",
    "source": "NPR",
    "published": "2026-02-20T19:22:29+00:00"
  },
  {
    "title": "Bishop of Lincoln arrested in sexual assault inquiry",
    "link": "https://www.bbc.com/news/articles/c5y5e32vwdwo?at_medium=RSS&at_campaign=rss",
    "source": "BBC News",
    "published": "2026-02-20T19:13:34+00:00"
  },
  {
    "title": "The Supreme Court Delivers Trump a Humiliating Gift",
    "link": "https://www.theatlantic.com/ideas/2026/02/supreme-court-tariffs-decision/686085/?utm_source=feed",
    "source": "The Atlantic",
    "published": "2026-02-20T19:10:00+00:00"
  },
  {
    "title": "These Skiers Cleared Out as Group That Would Be Hit by Avalanche Arrived",
    "link": "https://www.nytimes.com/2026/02/20/us/avalanche-tahoe-huts.html",
    "source": "New York Times",
    "published": "2026-02-20T19:08:27+00:00"
  },
  {
    "title": "What happens next for Andrew Mountbatten-Windsor?",
    "link": "https://www.bbc.com/news/videos/cgmljz14lpro?at_medium=RSS&at_campaign=rss",
    "source": "BBC News",
    "published": "2026-02-20T18:32:39+00:00"
  },
  {
    "title": "Get Ready for Zombie Tariffs",
    "link": "https://www.theatlantic.com/economy/2026/02/supreme-court-trump-tariffs/686083/?utm_source=feed",
    "source": "The Atlantic",
    "published": "2026-02-20T18:31:00+00:00"
  },
  {
    "title": "Portfolios assigned to eight advisers PM Tarique",
    "link": "https://www.tbsnews.net/bangladesh/portfolios-assigned-eight-advisers-new-govt-1367101",
    "source": "The Business Standard",
    "published": "2026-02-20T18:25:00+00:00"
  },
  {
    "title": "After dominant 6-2 win, the U.S. will face Canada for Olympic men's hockey gold",
    "link": "https://www.npr.org/2026/02/20/nx-s1-5720937/u-s-mens-hockey-slovakia-olympic-gold-medal",
    "source": "NPR",
    "published": "2026-02-20T18:23:34+00:00"
  },
  {
    "title": "Met asks Andrew's protection officers what they saw or heard in Epstein inquiry",
    "link": "https://www.bbc.com/news/articles/c05v77mv69vo?at_medium=RSS&at_campaign=rss",
    "source": "BBC News",
    "published": "2026-02-20T18:11:43+00:00"
  },
  {
    "title": "NASA eyes March 6 to launch 4 astronauts to the moon on Artemis II mission",
    "link": "https://www.npr.org/2026/02/20/nx-s1-5720953/nasa-artemis-ii-moon-launch-date",
    "source": "NPR",
    "published": "2026-02-20T18:06:30+00:00"
  },
  {
    "title": "Andrew and King Charles: A personal battle of royal brothers",
    "link": "https://www.bbc.com/news/articles/czx4y1l1nq4o?at_medium=RSS&at_campaign=rss",
    "source": "BBC News",
    "published": "2026-02-20T18:05:35+00:00"
  },
  {
    "title": "Vegetable, poultry prices surge during Ramadan",
    "link": "https://www.tbsnews.net/bangladesh/vegetable-poultry-prices-surge-during-ramadan-1367091",
    "source": "The Business Standard",
    "published": "2026-02-20T18:05:00+00:00"
  },
  {
    "title": "Four men, one aim - to end 102-year wait for Winter Olympic curling gold",
    "link": "https://www.bbc.com/sport/articles/ce3gqz1yyyyo?at_medium=RSS&at_campaign=rss",
    "source": "BBC News",
    "published": "2026-02-20T17:30:20+00:00"
  },
  {
    "title": "On pins and needles: Why Olympians pass the time knitting",
    "link": "https://www.npr.org/2026/02/20/nx-s1-5720897/olympics-ben-ogden-knitting",
    "source": "NPR",
    "published": "2026-02-20T17:29:31+00:00"
  },
  {
    "title": "Winners of the 2026 World Nature Photography Awards",
    "link": "https://www.theatlantic.com/photography/2026/02/winners-2026-world-nature-photography-awards/686078/?utm_source=feed",
    "source": "The Atlantic",
    "published": "2026-02-20T17:17:08+00:00"
  },
  {
    "title": "Epstein Scandal Leaves Some Young Trump Voters Feeling Betrayed",
    "link": "https://www.nytimes.com/2026/02/20/style/epstein-files-young-conservatives.html",
    "source": "New York Times",
    "published": "2026-02-20T17:15:39+00:00"
  },
  {
    "title": "U.K. considers cutting ex-Prince Andrew from line of succession over his Epstein ties",
    "link": "https://www.npr.org/2026/02/20/g-s1-110915/uk-former-prince-andrew-epstein-investigation",
    "source": "NPR",
    "published": "2026-02-20T16:51:35+00:00"
  },
  {
    "title": "PM, president, opposition leaders pay tribute to 1952 language martyrs",
    "link": "https://www.tbsnews.net/bangladesh/pm-president-pay-tribute-1952-language-martyrs-shaheed-minar-1367096",
    "source": "The Business Standard",
    "published": "2026-02-20T16:35:00+00:00"
  },
  {
    "title": "Artificial crises in food, agri sector to be dealt properly: Salauddin Tuku",
    "link": "https://www.tbsnews.net/bangladesh/artificial-crises-food-agri-sector-be-dealt-properly-salauddin-tuku-1367081",
    "source": "The Business Standard",
    "published": "2026-02-20T16:20:00+00:00"
  },
  {
    "title": "A tip-off and 'more luck than judgement': The story behind Andrew car snap",
    "link": "https://www.bbc.com/news/articles/c93wl4kp671o?at_medium=RSS&at_campaign=rss",
    "source": "BBC News",
    "published": "2026-02-20T16:09:03+00:00"
  },
  {
    "title": "Colourful cauliflower cultivation changes fortunes of Dumuria farmers",
    "link": "https://www.tbsnews.net/bangladesh/colourful-cauliflower-cultivation-changes-fortunes-dumuria-farmers-1367076",
    "source": "The Business Standard",
    "published": "2026-02-20T16:00:00+00:00"
  },
  {
    "title": "The Big Story: Signalgate, One Year Later",
    "link": "https://www.theatlantic.com/national-security/2026/02/big-story-signalgate-one-year-later-jeffrey-goldberg/686072/?utm_source=feed",
    "source": "The Atlantic",
    "published": "2026-02-20T15:48:00+00:00"
  },
  {
    "title": "How Eric Dane gave his final months to 'moving the needle' on ALS",
    "link": "https://www.bbc.com/news/articles/c24d9vpjmnmo?at_medium=RSS&at_campaign=rss",
    "source": "BBC News",
    "published": "2026-02-20T15:46:25+00:00"
  },
  {
    "title": "7 key things to know about Trump's tariffs after the Supreme Court decision",
    "link": "https://www.npr.org/2026/02/20/nx-s1-5677609/tariffs-economy-trump-supreme-court",
    "source": "NPR",
    "published": "2026-02-20T15:38:13+00:00"
  },
  {
    "title": "Govt working to ensure uninterrupted power during Ramadan: State minister",
    "link": "https://www.tbsnews.net/bangladesh/energy/govt-working-ensure-uninterrupted-power-during-ramadan-state-minister-1367056",
    "source": "The Business Standard",
    "published": "2026-02-20T15:35:00+00:00"
  },
  {
    "title": "Neutral athletes allowed to attend closing ceremony",
    "link": "https://www.bbc.com/sport/articles/c2041rem5j4o?at_medium=RSS&at_campaign=rss",
    "source": "BBC News",
    "published": "2026-02-20T15:32:36+00:00"
  },
  {
    "title": "How Andrew's 11-hour detention on his birthday played out",
    "link": "https://www.bbc.com/news/articles/cz9qy5057e0o?at_medium=RSS&at_campaign=rss",
    "source": "BBC News",
    "published": "2026-02-20T15:28:09+00:00"
  },
  {
    "title": "Facing a mental health crisis, an NJ school pulled a beloved novel from English class",
    "link": "https://www.npr.org/2026/02/20/nx-s1-5708741/junot-diaz-oscar-wao-mental-health-book-bans",
    "source": "NPR",
    "published": "2026-02-20T15:27:25+00:00"
  },
  {
    "title": "India looks to strengthen ties with Bangladesh in 'positive direction'",
    "link": "https://www.tbsnews.net/bangladesh/india-looks-strengthen-ties-bangladesh-positive-direction-1367046",
    "source": "The Business Standard",
    "published": "2026-02-20T15:25:00+00:00"
  },
  {
    "title": "Jamaat chief questions if extortion 'declared nationalised' thru Minister Rabiul",
    "link": "https://www.tbsnews.net/bangladesh/jamaat-chief-questions-if-extortion-declared-nationalised-thru-minister-rabiul-1367041",
    "source": "The Business Standard",
    "published": "2026-02-20T15:15:00+00:00"
  },
  {
    "title": "Coast Guard rescues 55 during anti-trafficking drive in Teknaf",
    "link": "https://www.tbsnews.net/bangladesh/coast-guard-rescues-55-during-anti-trafficking-drive-teknaf-1367031",
    "source": "The Business Standard",
    "published": "2026-02-20T14:55:00+00:00"
  },
  {
    "title": "The AI-Panic Cycle\u2014And What\u2019s Actually Different Now",
    "link": "https://www.theatlantic.com/podcasts/2026/02/the-ai-panic-cycle-and-whats-actually-different-now/686077/?utm_source=feed",
    "source": "The Atlantic",
    "published": "2026-02-20T14:35:06+00:00"
  },
  {
    "title": "Democratic values, people's rights core spirit of Ekushey: PM Tarique",
    "link": "https://www.tbsnews.net/bangladesh/democratic-values-peoples-rights-core-spirit-ekushey-pm-tarique-1367016",
    "source": "The Business Standard",
    "published": "2026-02-20T14:30:00+00:00"
  },
  {
    "title": "Our Olympians Are Being Put in an Impossible Position",
    "link": "https://www.theatlantic.com/ideas/2026/02/winter-olympics-politics-trump-speech-protest/686046/?utm_source=feed",
    "source": "The Atlantic",
    "published": "2026-02-20T14:00:00+00:00"
  },
  {
    "title": "<em>The Washington Post</em>\u2019s Leaders Missed the Point",
    "link": "https://www.theatlantic.com/books/2026/02/the-washington-posts-books-section-worked/686070/?utm_source=feed",
    "source": "The Atlantic",
    "published": "2026-02-20T13:00:00+00:00"
  },
  {
    "title": "An Extraordinary Account of a Dangerous Marriage",
    "link": "https://www.theatlantic.com/books/2026/02/gisele-pelicot-hymn-to-life-memoir/686045/?utm_source=feed",
    "source": "The Atlantic",
    "published": "2026-02-20T12:30:00+00:00"
  },
  {
    "title": "The \u2018Existential Anxiety\u2019 of the Islamic Republic",
    "link": "https://www.theatlantic.com/international/2026/02/iran-opposition-unite/686050/?utm_source=feed",
    "source": "The Atlantic",
    "published": "2026-02-20T12:00:00+00:00"
  },
  {
    "title": "A Once Prominent American Statesman Faces Fallout From the Epstein Files",
    "link": "https://www.nytimes.com/2026/02/20/us/epstein-george-mitchell-ireland-maine.html",
    "source": "New York Times",
    "published": "2026-02-20T10:02:53+00:00"
  },
  {
    "title": "A.I. Isn\u2019t Coming for Every White-Collar Job. At Least Not Yet.",
    "link": "https://www.nytimes.com/2026/02/20/technology/ai-coding-software-jobs.html",
    "source": "New York Times",
    "published": "2026-02-20T10:01:01+00:00"
  }
]